{"name":"自编故事","slug":"自编故事","count":1,"postlist":[{"title":"《光明之火，照亮前行的道路》","uid":"2b0b2c1918b3312281b080ee58865308","slug":"《光明之火，照亮前行的道路》","date":"2024-12-14T08:44:43.000Z","updated":"2024-12-14T08:59:06.604Z","comments":true,"path":"api/articles/《光明之火，照亮前行的道路》.json","keywords":null,"cover":null,"text":"人物介绍(1)李尽程：热爱文学，善于帮助父母做一些力所能及的家务，学习成绩一般，但永远不会放弃，对自己的未来充满希望。(2)李修革：李尽程的父亲，对待李尽程十分...","permalink":"/post/《光明之火，照亮前行的道路》","photos":[],"count_time":{"symbolsCount":"2k","symbolsTime":"2 mins."},"categories":[],"tags":[{"name":"自编故事","slug":"自编故事","count":1,"path":"api/tags/自编故事.json"}],"author":{"name":"Jag Canhai","slug":"blog-author","avatar":"https://replit.com/@L1896828766/jagcanhaigithubio-image#image/ubuntu22.10.png","link":"/","description":"一位热爱Ubuntu的爱好者","socials":{"github":"","twitter":"","stackoverflow":"","wechat":"","qq":"","weibo":"","zhihu":"","csdn":"","juejin":"","customs":{}}},"feature":true}]}